Workbook

Sheet Summary
A1: D Sculpt Fitness — Production Test Run
A3: Tester | E3: How to use
A4: Date started
A5: Build / URL tested | E5: 1. Work through the "Test Runs" tab top to bottom.
A6: Finance All-Time revenue BEFORE testing | E6: 2. Set Result to Pass / Fail / Blocked / Not tested (dropdown).
A7: Finance All-Time revenue AFTER cleanup | E7: 3. On a Fail, write the ACTUAL numbers you saw in "Actual / notes" —
A8: Member count BEFORE / AFTER | E8: not "wrong", but "Finance showed Rs 7,500, expected Rs 5,000".
E9: 4. Set Severity on every Fail.
A10: Results | E10: 5. Money wrong, two screens disagreeing, or a member seeing data
A11: Total tests | B11: =COUNTA('Test Runs'!A2:A196)-COUNTBLANK('Test Runs'!C2:C196) -> 176 | E11: that is not theirs = Major at minimum.
A12: Pass | B12: =COUNTIF('Test Runs'!F2:F196,"Pass") -> 0 | E12: 6. Screenshot every failure, including the browser console (F12).
A13: Fail | B13: =COUNTIF('Test Runs'!F2:F196,"Fail") -> 0 | E13: 7. Prefix all test data with ZZTEST- and delete it at the end (section 18).
A14: Blocked | B14: =COUNTIF('Test Runs'!F2:F196,"Blocked") -> 0
A15: Not tested | B15: =COUNTIF('Test Runs'!F2:F196,"Not tested") -> 0
A16: Blockers | B16: =COUNTIF('Test Runs'!H2:H196,"Blocker") -> 0
A17: Majors | B17: =COUNTIF('Test Runs'!H2:H196,"Major") -> 0
A18: Minors | B18: =COUNTIF('Test Runs'!H2:H196,"Minor") -> 0
A21: By area — failures
A22: Area | B22: Fail | C22: Blocker+Major
A23: 0 | B23: =COUNTIFS('Test Runs'!B2:B196,A23,'Test Runs'!F2:F196,"Fail") -> 0 | C23: =COUNTIFS('Test Runs'!B2:B196,A23,'Test Runs'!H2:H196,"Blocker")+COUNTIFS('Test Runs'!B2:B196,A23,'Test Runs'!H2:H196,"Major") -> 0
A24: 1 | B24: =COUNTIFS('Test Runs'!B2:B196,A24,'Test Runs'!F2:F196,"Fail") -> 0 | C24: =COUNTIFS('Test Runs'!B2:B196,A24,'Test Runs'!H2:H196,"Blocker")+COUNTIFS('Test Runs'!B2:B196,A24,'Test Runs'!H2:H196,"Major") -> 0
A25: 2 | B25: =COUNTIFS('Test Runs'!B2:B196,A25,'Test Runs'!F2:F196,"Fail") -> 0 | C25: =COUNTIFS('Test Runs'!B2:B196,A25,'Test Runs'!H2:H196,"Blocker")+COUNTIFS('Test Runs'!B2:B196,A25,'Test Runs'!H2:H196,"Major") -> 0
A26: 3 | B26: =COUNTIFS('Test Runs'!B2:B196,A26,'Test Runs'!F2:F196,"Fail") -> 0 | C26: =COUNTIFS('Test Runs'!B2:B196,A26,'Test Runs'!H2:H196,"Blocker")+COUNTIFS('Test Runs'!B2:B196,A26,'Test Runs'!H2:H196,"Major") -> 0
A27: 4 | B27: =COUNTIFS('Test Runs'!B2:B196,A27,'Test Runs'!F2:F196,"Fail") -> 0 | C27: =COUNTIFS('Test Runs'!B2:B196,A27,'Test Runs'!H2:H196,"Blocker")+COUNTIFS('Test Runs'!B2:B196,A27,'Test Runs'!H2:H196,"Major") -> 0
A28: 5 | B28: =COUNTIFS('Test Runs'!B2:B196,A28,'Test Runs'!F2:F196,"Fail") -> 0 | C28: =COUNTIFS('Test Runs'!B2:B196,A28,'Test Runs'!H2:H196,"Blocker")+COUNTIFS('Test Runs'!B2:B196,A28,'Test Runs'!H2:H196,"Major") -> 0
A29: 6 | B29: =COUNTIFS('Test Runs'!B2:B196,A29,'Test Runs'!F2:F196,"Fail") -> 0 | C29: =COUNTIFS('Test Runs'!B2:B196,A29,'Test Runs'!H2:H196,"Blocker")+COUNTIFS('Test Runs'!B2:B196,A29,'Test Runs'!H2:H196,"Major") -> 0
A30: 7 | B30: =COUNTIFS('Test Runs'!B2:B196,A30,'Test Runs'!F2:F196,"Fail") -> 0 | C30: =COUNTIFS('Test Runs'!B2:B196,A30,'Test Runs'!H2:H196,"Blocker")+COUNTIFS('Test Runs'!B2:B196,A30,'Test Runs'!H2:H196,"Major") -> 0
A31: 8 | B31: =COUNTIFS('Test Runs'!B2:B196,A31,'Test Runs'!F2:F196,"Fail") -> 0 | C31: =COUNTIFS('Test Runs'!B2:B196,A31,'Test Runs'!H2:H196,"Blocker")+COUNTIFS('Test Runs'!B2:B196,A31,'Test Runs'!H2:H196,"Major") -> 0
A32: 9 | B32: =COUNTIFS('Test Runs'!B2:B196,A32,'Test Runs'!F2:F196,"Fail") -> 0 | C32: =COUNTIFS('Test Runs'!B2:B196,A32,'Test Runs'!H2:H196,"Blocker")+COUNTIFS('Test Runs'!B2:B196,A32,'Test Runs'!H2:H196,"Major") -> 0
A33: 10 | B33: =COUNTIFS('Test Runs'!B2:B196,A33,'Test Runs'!F2:F196,"Fail") -> 0 | C33: =COUNTIFS('Test Runs'!B2:B196,A33,'Test Runs'!H2:H196,"Blocker")+COUNTIFS('Test Runs'!B2:B196,A33,'Test Runs'!H2:H196,"Major") -> 0
A34: 11 | B34: =COUNTIFS('Test Runs'!B2:B196,A34,'Test Runs'!F2:F196,"Fail") -> 0 | C34: =COUNTIFS('Test Runs'!B2:B196,A34,'Test Runs'!H2:H196,"Blocker")+COUNTIFS('Test Runs'!B2:B196,A34,'Test Runs'!H2:H196,"Major") -> 0
A35: 12 | B35: =COUNTIFS('Test Runs'!B2:B196,A35,'Test Runs'!F2:F196,"Fail") -> 0 | C35: =COUNTIFS('Test Runs'!B2:B196,A35,'Test Runs'!H2:H196,"Blocker")+COUNTIFS('Test Runs'!B2:B196,A35,'Test Runs'!H2:H196,"Major") -> 0
A36: 13 | B36: =COUNTIFS('Test Runs'!B2:B196,A36,'Test Runs'!F2:F196,"Fail") -> 0 | C36: =COUNTIFS('Test Runs'!B2:B196,A36,'Test Runs'!H2:H196,"Blocker")+COUNTIFS('Test Runs'!B2:B196,A36,'Test Runs'!H2:H196,"Major") -> 0
A37: 14 | B37: =COUNTIFS('Test Runs'!B2:B196,A37,'Test Runs'!F2:F196,"Fail") -> 0 | C37: =COUNTIFS('Test Runs'!B2:B196,A37,'Test Runs'!H2:H196,"Blocker")+COUNTIFS('Test Runs'!B2:B196,A37,'Test Runs'!H2:H196,"Major") -> 0
A38: 15 | B38: =COUNTIFS('Test Runs'!B2:B196,A38,'Test Runs'!F2:F196,"Fail") -> 0 | C38: =COUNTIFS('Test Runs'!B2:B196,A38,'Test Runs'!H2:H196,"Blocker")+COUNTIFS('Test Runs'!B2:B196,A38,'Test Runs'!H2:H196,"Major") -> 0
A39: 16 | B39: =COUNTIFS('Test Runs'!B2:B196,A39,'Test Runs'!F2:F196,"Fail") -> 0 | C39: =COUNTIFS('Test Runs'!B2:B196,A39,'Test Runs'!H2:H196,"Blocker")+COUNTIFS('Test Runs'!B2:B196,A39,'Test Runs'!H2:H196,"Major") -> 0
A40: 17 | B40: =COUNTIFS('Test Runs'!B2:B196,A40,'Test Runs'!F2:F196,"Fail") -> 0 | C40: =COUNTIFS('Test Runs'!B2:B196,A40,'Test Runs'!H2:H196,"Blocker")+COUNTIFS('Test Runs'!B2:B196,A40,'Test Runs'!H2:H196,"Major") -> 0
A41: 18 | B41: =COUNTIFS('Test Runs'!B2:B196,A41,'Test Runs'!F2:F196,"Fail") -> 0 | C41: =COUNTIFS('Test Runs'!B2:B196,A41,'Test Runs'!H2:H196,"Blocker")+COUNTIFS('Test Runs'!B2:B196,A41,'Test Runs'!H2:H196,"Major") -> 0

Sheet Test Runs
A1: ID | B1: Area | C1: What to do | D1: What must happen | E1: Why it matters | F1: Result | G1: Actual / notes | H1: Severity | I1: Tester | J1: Date
A2: 0 · Before you start — environment sanity
A3: 0.1 | B3: 0 | C3: Open the production URL in a fresh incognito window | D3: Landing page loads, no console errors, logo and photos render
A4: 0.2 | B4: 0 | C4: Hard-refresh the dashboard 3 times in a row | D4: Never lands on the landing page or a blank screen. (A router race used to do exactly this)
A5: 0.3 | B5: 0 | C5: Open the app, then go offline (airplane mode), then click around | D5: Clear "offline" messaging, not a white screen or a silent failure
A6: 0.4 | B6: 0 | C6: Check the browser console on every page you visit today | D6: Zero red errors. Note any that appear
A7: 0.5 | B7: 0 | C7: Install as a PWA (Add to Home Screen) and open it | D7: Opens standalone, icon correct, works
A8: 0.6 | B8: 0 | C8: Log in, log out, log in again | D8: Second login works without clearing cache
A9: 1 · Member login (member portal)
A10: 1.1 | B10: 1 | C10: Add a brand-new member as owner. **Write down the application number shown.** | D10: The application number is shown clearly after saving and is not blank/`—`/`null` | E10: Members were being created with no application number at all, so they could never log in and nobody knew
A11: 1.2 | B11: 1 | C11: Log in to the member portal with that number + phone | D11: Lands on the member portal
A12: 1.3 | B12: 1 | C12: Log in as a member who was created **weeks ago**, not today | D12: Works too | E12: Old members and new members go through different code paths
A13: 1.4 | B13: 1 | C13: Type the phone **with +91**, with spaces, with a leading 0 | D13: All three work | E13: People paste from Contacts
A14: 1.5 | B14: 1 | C14: Type the application number in lowercase | D14: Works
A15: 1.6 | B15: 1 | C15: Wrong application number, correct phone | D15: Generic error. Must **not** say which field was wrong | E15: Saying "phone is wrong" tells an attacker the number is real
A16: 1.7 | B16: 1 | C16: Correct application number, wrong phone | D16: **Exactly the same** error text as 1.6 | E16: Any difference is a security hole
A17: 1.8 | B17: 1 | C17: Fail login 6 times in a row | D17: Locks out with a "too many attempts" message
A18: 1.9 | B18: 1 | C18: After lockout, wait it out and log in correctly | D18: Works again — you are not locked out permanently
A19: 1.10 | B19: 1 | C19: **Edit that member** (change anything — name, notes, photo) and save. Then log in as them again | D19: Login still works | E19: Editing a member has previously overwritten the application number with blank and silently locked them out. This is the single highest-value test on this page
A20: 1.11 | B20: 1 | C20: Regenerate a member's application number, then try the **old** number | D20: Old number rejected, new number works
A21: 1.12 | B21: 1 | C21: Log in as member A, then log out and log in as member B on the same device | D21: B sees only B's data. No trace of A's name, plan, receipts or visits anywhere
A22: 1.13 | B22: 1 | C22: While logged in as a member, look for anything owner-only: the Add Member button, sidebar, finance figures | D22: Nothing owner-only visible. The floating "+" button in particular has leaked into the member portal before
A23: 1.14 | B23: 1 | C23: Member portal → all four tabs (Check In, My Plan, Receipts, Visits) | D23: All render, nothing blank, no console errors
A24: 1.15 | B24: 1 | C24: Log in as a member whose membership is **expired** | D24: Shows "expired X days ago" — never a negative number like "-5 days remaining" | E24: Fixed once; check both the My Plan tab and the Check In tab, they were separate bugs
A25: 2 · Add member → the money must appear everywhere
A26: 2.1 | B26: 2 | C26: Add `ZZTEST-A` on a ₹2,500 plan, fully paid, Cash | D26: Saves, success message, application number shown
A27: 2.2 | B27: 2 | C27: Members list | D27: Appears, correct plan, correct status, correct expiry
A28: 2.3 | B28: 2 | C28: Finance → This Month | D28: Revenue went up by **exactly ₹2,500**. Cash total went up by ₹2,500. Card and Online unchanged
A29: 2.4 | B29: 2 | C29: Overview | D29: Revenue figure matches Finance. Member count went up by 1
A30: 2.5 | B30: 2 | C30: Open the member → payment history | D30: One payment, ₹2,500, Cash, today's date
A31: 2.6 | B31: 2 | C31: Generate the invoice | D31: Amount ₹2,500, correct name, correct gym details, correct GST treatment
A32: 2.7 | B32: 2 | C32: Hard-refresh, re-check Finance and Overview | D32: Same numbers. Nothing drifted
A33: 2.8 | B33: 2 | C33: Plan **+ an add-on** (e.g. ₹2,500 plan + ₹300 cardio) | D33: Member detail modal must show ₹2,500 plan / ₹300 add-on / **₹2,800 total** — not ₹2,800 plan and ₹3,100 total. Add-ons were being counted twice in the modal while the invoice and DB were correct
A34: 2.9 | B34: 2 | C34: **Partial payment** — ₹2,500 plan, ₹1,000 paid now | D34: Finance revenue +₹1,000 (not ₹2,500). Pending Dues +₹1,500. Member status "Partial". Alerts → Due shows them
A35: 2.10 | B35: 2 | C35: **Zero paid / full due** | D35: Revenue unchanged. Dues +₹2,500
A36: 2.11 | B36: 2 | C36: **With a discount** | D36: Invoice, member modal and Finance all agree on the discounted figure
A37: 2.12 | B37: 2 | C37: **Trial member** | D37: Expiry is the trial date you set, not a plan-derived date. Doesn't pollute revenue if unpaid
... A44: 2.19 | B44: 2 | C44: Name with an apostrophe (`ZZTEST-O'Brien`) and one with `<b>bold</b>` in it | D44: Displays literally. No broken layout, no bold text rendering, no crash. Check the list, the modal, the invoice and the CSV export
A45: 3 · Delete / remove a member
A46: 3.1 | B46: 3 | C46: Add `ZZTEST-B` with a ₹2,000 payment. Note Finance revenue
A47: 3.2 | B47: 3 | C47: **Remove** the member (the normal soft delete) | D47: Gone from Members list, gone from Alerts, gone from member count
A48: 3.3 | B48: 3 | C48: Check Finance immediately, then after a hard refresh | D48: Revenue **still includes** the ₹2,000 — this is correct and deliberate. The screen must *say so* somewhere, so the owner isn't left thinking it's a bug
A49: 3.4 | B49: 3 | C49: Use **Delete permanently** on another test member with a payment | D49: Revenue drops by exactly that member's payments. Member, payments, invoices and check-ins all gone
A50: 3.5 | B50: 3 | C50: Try Delete permanently as **staff** 🔒 | D50: Not available / refused
A51: 3.6 | B51: 3 | C51: Delete permanently, then hard refresh, then check Finance, Overview, Analytics, and the Payments CSV export | D51: All five agree that the money is gone. Not "gone in Finance, still in Analytics"
A52: 3.7 | B52: 3 | C52: Remove a member, then check the Payments/Members CSV export and the Full Backup | D52: The removed member is handled consistently — either present-and-marked or absent, in *every* export, not different per file
A53: 3.8 | B53: 3 | C53: Remove a member who has an **outstanding balance** | D53: Pending Dues drops by their balance. Alerts count drops
A54: 3.9 | B54: 3 | C54: Cancel a membership (not delete) | D54: Different from remove: check what Finance, Alerts and the member's own portal each show
A55: 3.10 | B55: 3 | C55: Remove the **last remaining** member | D55: Finance/Overview show ₹0 or empty states cleanly, not "NaN", "undefined" or a broken chart
A56: 4 · Renewals
A57: 4.1 | B57: 4 | C57: Renew a member **before** their expiry, same plan, same price | D57: Succeeds. New expiry = old expiry + plan duration (**not** today + duration — they must not lose the days they'd already paid for)
A58: 4.2 | B58: 4 | C58: **Renew the same member again** on the same plan and price a minute later | D58: Must succeed. This exact case was permanently blocked as a "duplicate" — the single most common real-world pattern
A59: 4.3 | B59: 4 | C59: Renew a member **after** expiry | D59: New expiry counts from today, not from the old expired date
A60: 4.4 | B60: 4 | C60: Double-click the Renew confirm button | D60: Exactly one renewal, one payment
A61: 4.5 | B61: 4 | C61: After each renewal: Finance, Overview, payment history, invoice, member's own portal | D61: All show the new payment and the new expiry. All agree
A62: 4.6 | B62: 4 | C62: Renew onto a **different, more expensive** plan | D62: Amount, expiry and plan name all update everywhere
A63: 4.7 | B63: 4 | C63: Renew with a partial payment | D63: Balance due created correctly, appears in Alerts and Finance Pending Dues
A64: 4.8 | B64: 4 | C64: Renew a **cancelled** member | D64: Either sensibly reactivates them or is blocked with a clear message — not a silent failure
A65: 5 · Collecting a pending balance
A66: 5.1 | B66: 5 | C66: Member with ₹1,500 due — collect ₹500 | D66: Balance now ₹1,000. Status stays Partial. Finance revenue +₹500. Dues −₹500
A67: 5.2 | B67: 5 | C67: Collect the remaining ₹1,000 | D67: Balance ₹0, status Paid, member leaves the Alerts→Due list
A68: 5.3 | B68: 5 | C68: Try to collect **more** than the balance | D68: Blocked or handled sensibly — never a negative balance
A69: 5.4 | B69: 5 | C69: Try to collect ₹0 or a negative amount | D69: Blocked
A70: 5.5 | B70: 5 | C70: Open the same member on two devices/tabs and collect at the same time | D70: Money counted once, not twice
A71: 5.6 | B71: 5 | C71: After collecting, check the invoice and payment history | D71: Both show the new payment separately from the original
A72: 5.7 | B72: 5 | C72: As staff 🔒 collect a balance | D72: Allowed (staff can collect) — but the Finance page must still be blocked for them
A73: 6 · Finance page
A74: 6.1 | B74: 6 | C74: Click through every period: Today / This Week / This Month / Last Month / Calendar Year / All Time | D74: Each loads, no console errors, figures change sensibly
A75: 6.2 | B75: 6 | C75: Add up: does Cash + Card + Online = total Revenue? | D75: Yes, in every period
A76: 6.3 | B76: 6 | C76: Net Profit = Revenue − Expenses? | D76: Check by hand for one period
A77: 6.4 | B77: 6 | C77: "All Time" revenue vs the sum of every month | D77: Must reconcile
A78: 6.5 | B78: 6 | C78: Custom range: pick a range that contains a known payment | D78: That payment is included. Check both boundary days — the first and last day of the range must be inclusive. Off-by-one on the end date has broken this before
A79: 6.6 | B79: 6 | C79: Custom range with **end date before start date** | D79: Blocked or handled, not a crash or a nonsense number
A80: 6.7 | B80: 6 | C80: Add an expense dated **today**, check This Month; then change it to last month | D80: Moves between periods correctly
A81: 6.8 | B81: 6 | C81: Pending Dues card | D81: It is **all-time**, not period-scoped. Confirm the label says so and the number matches the sum of every member's balance
A82: 6.9 | B82: 6 | C82: Click each stat card to expand the detail | D82: Rows shown match the total above them
A83: 6.10 | B83: 6 | C83: Export CSV | D83: Opens in Excel. Rows match what's on screen. Member names with commas/apostrophes don't break the columns. Filename sensible
A84: 6.11 | B84: 6 | C84: The 6-month Revenue vs Expenses chart | D84: Doesn't change when you change the period buttons (it's a fixed 6-month trend) — and the label must say so
A85: 6.12 | B85: 6 | C85: As staff 🔒 try to reach Finance (sidebar and by typing the URL `/dashboard/finance`) | D85: Blocked both ways
A86: 7 · Expenses
A87: 7.1 | B87: 7 | C87: Add an expense, check Finance | D87: Expenses total and Net Profit both move
A88: 7.2 | B88: 7 | C88: Edit its amount | D88: Finance updates
A89: 7.3 | B89: 7 | C89: Delete it | D89: Finance returns to the previous figure exactly
A90: 7.4 | B90: 7 | C90: Expense on the **1st** and on the **last day** of a month | D90: Both land in the right month. Month-boundary handling has broken here before
A91: 7.5 | B91: 7 | C91: Category name with `<script>` or `&` in it | D91: Displays literally, does not break the page (this exact spot had an XSS bug)
A92: 7.6 | B92: 7 | C92: Very large amount, and a decimal amount (₹99.50) | D92: Stored and displayed correctly, rounding consistent everywhere
A93: 7.7 | B93: 7 | C93: As staff 🔒 | D93: Can add, **cannot** edit or delete
A94: 8 · Check-in (desk display + scanner)
A95: 8.1 | B95: 8 | C95: Open the desk display | D95: QR appears, refreshes on its own (watch for ~1 min), screen doesn't sleep
A96: 8.2 | B96: 8 | C96: Press the **Back** button on the desk display | D96: Returns to the dashboard **on the first press**. This is the button that failed at the client site
A97: 8.3 | B97: 8 | C97: Go to another section and come back to the desk display, then press Back again | D97: Still works. The earlier failure only appeared after navigating around first
A98: 8.4 | B98: 8 | C98: Scan the QR from the member portal as an **active** member | D98: Check-in succeeds, confirmation shown
A99: 8.5 | B99: 8 | C99: Scan again immediately | D99: Handled — either a friendly "already checked in" or counted once. Never two visits for one entry
A100: 8.6 | B100: 8 | C100: Scan as an **expired** member | D100: Rejected with a clear reason
A101: 8.7 | B101: 8 | C101: Scan a QR screenshot taken **2+ minutes ago** | D101: Rejected (codes expire)
A102: 8.8 | B102: 8 | C102: Check in early morning (before 6am if you can) or change device time | D102: The visit lands on today's date in India time, not yesterday. UTC/IST slippage has broken this class of thing before
A103: 8.9 | B103: 8 | C103: Staff manual check-in | D103: Works, appears in Check-ins list
A104: 8.10 | B104: 8 | C104: After check-ins: Check-ins page, the member's Visits tab, and the attendance report | D104: All show the same visits, same count, same dates
A105: 8.11 | B105: 8 | C105: Leave the desk display open for 10 minutes | D105: Still refreshing, no memory bloat, no console errors piling up
A106: 8.12 | B106: 8 | C106: Desk display with wifi off | D106: Shows the offline warning, doesn't show a stale QR as if it were valid
...
